{
  "componentGuid": "38870ec0-3e64-996e-7d78-9f4213cbe51e",
  "componentType": "IfcPropertySetComponent",
  "entityGuid": "90b5427d-746e-40f4-80ed-1e918f8eaab8",
  "hasProperties": [
    {
      "componentType": "IfcPropertyEnumeratedValueComponent",
      "enumerationValues": [
        {
          "componentType": "IfcLabelComponent",
          "wrappedValue": "RECTANGULAR"
        }
      ],
      "name": "Shape"
    },
    {
      "componentType": "IfcPropertySingleValueComponent",
      "name": "Length",
      "nominalValue": {
        "componentType": "IfcPositiveLengthMeasureComponent",
        "wrappedValue": 114.39999999999294
      }
    }
  ],
  "name": "Pset_DuctSegmentTypeCommon"
}