{
  "componentGuid": "c15d142a-a328-aa6b-f4b1-38e69260ce76",
  "componentType": "IfcPropertySetComponent",
  "entityGuid": "2224301a-205e-43be-8b69-668f1a1561b8",
  "hasProperties": [
    {
      "componentType": "IfcPropertySingleValueComponent",
      "name": "IsExternal",
      "nominalValue": {
        "componentType": "IfcBooleanComponent",
        "wrappedValue": true
      }
    },
    {
      "componentType": "IfcPropertySingleValueComponent",
      "name": "ExtendToStructure",
      "nominalValue": {
        "componentType": "IfcBooleanComponent",
        "wrappedValue": false
      }
    },
    {
      "componentType": "IfcPropertySingleValueComponent",
      "name": "LoadBearing",
      "nominalValue": {
        "componentType": "IfcBooleanComponent",
        "wrappedValue": false
      }
    },
    {
      "componentType": "IfcPropertySingleValueComponent",
      "name": "Reference",
      "nominalValue": {
        "componentType": "IfcIdentifierComponent",
        "wrappedValue": "CASE - 24\" Concrete"
      }
    }
  ],
  "name": "Pset_WallCommon"
}