{
  "componentGuid": "ed96cd0f-4dab-0d35-4ecc-527a0557cb35",
  "componentType": "IfcPropertySetComponent",
  "entityGuid": "4406b2b1-1146-481f-817c-2a5e0fc3c3a3",
  "hasProperties": [
    {
      "componentType": "IfcPropertyEnumeratedValueComponent",
      "enumerationValues": [
        {
          "componentType": "IfcLabelComponent",
          "wrappedValue": "RECTANGULAR"
        }
      ],
      "name": "Shape"
    },
    {
      "componentType": "IfcPropertySingleValueComponent",
      "name": "Length",
      "nominalValue": {
        "componentType": "IfcPositiveLengthMeasureComponent",
        "wrappedValue": 1.9569909868278614
      }
    }
  ],
  "name": "Pset_DuctSegmentTypeCommon"
}