{
  "componentGuid": "200b1b96-8579-2740-9f45-33efd87d924b",
  "componentType": "IfcPropertySetComponent",
  "entityGuid": "87fabca8-6591-4813-84a7-fa1b325f89b2",
  "hasProperties": [
    {
      "componentType": "IfcPropertySingleValueComponent",
      "name": "IsExternal",
      "nominalValue": {
        "componentType": "IfcBooleanComponent",
        "wrappedValue": true
      }
    },
    {
      "componentType": "IfcPropertySingleValueComponent",
      "name": "Reference",
      "nominalValue": {
        "componentType": "IfcIdentifierComponent",
        "wrappedValue": "n/a"
      }
    },
    {
      "componentType": "IfcPropertySingleValueComponent",
      "name": "FireRating",
      "nominalValue": {
        "componentType": "IfcLabelComponent",
        "wrappedValue": "n/a"
      }
    }
  ],
  "name": "Pset_WindowCommon"
}